{"days":[{"day":"Monday","class":[{"name":"ศิลปะ","time_start":"08:20:00","time_end":"09:10:00"},{"name":"อังกฤษ อ่านเขียน","time_start":"09:10:00","time_end":"10:00:00"},{"name":"ประวัติศาสตร์","time_start":"10:00:00","time_end":"10:50:00"},{"name":"พัก","time_start":"10:50:00","time_end":"11:40:00"},{"name":"คณิตศาสตร์","time_start":"11:40:00","time_end":"12:30:00"},{"name":"สังคม","time_start":"12:30:00","time_end":"13:20:00"},{"name":"พลศึกษา","time_start":"13:20:00","time_end":"14:10:00"},{"name":"แนะแนว","time_start":"14:10:00","time_end":"15:00:00"}]},{"day":"Tuesday","class":[{"name":"วิชาเลือก","time_start":"08:20:00","time_end":"09:10:00"},{"name":"วิชาเลือก","time_start":"09:10:00","time_end":"10:00:00"},{"name":"วิทยาศาสตร์","time_start":"10:00:00","time_end":"10:50:00"},{"name":"พัก","time_start":"10:50:00","time_end":"11:40:00"},{"name":"อังกฤษ","time_start":"11:40:00","time_end":"12:30:00"},{"name":"ไทย","time_start":"12:30:00","time_end":"13:20:00"},{"name":"สุขศึกษา","time_start":"13:20:00","time_end":"14:10:00"},{"name":"การงาน","time_start":"14:10:00","time_end":"15:00:00"}]},{"day":"Wednesday","class":[{"name":"วิทยาศาสตร์","time_start":"08:20:00","time_end":"09:10:00"},{"name":"วิทยาศาสตร์","time_start":"09:10:00","time_end":"10:00:00"},{"name":"คณิตเพิ่มเติม","time_start":"10:00:00","time_end":"10:50:00"},{"name":"พัก","time_start":"10:50:00","time_end":"11:40:00"},{"name":"นาฏศิลป์","time_start":"11:40:00","time_end":"12:30:00"},{"name":"ไทย","time_start":"12:30:00","time_end":"13:20:00"},{"name":"อังกฤษ อ่านเขียน","time_start":"13:20:00","time_end":"14:10:00"}]},{"day":"Thursday","class":[{"name":"ไทย","time_start":"08:20:00","time_end":"09:10:00"},{"name":"คณิตศาสตร์","time_start":"09:10:00","time_end":"10:00:00"},{"name":"พระพุทธศาสนา","time_start":"10:00:00","time_end":"10:50:00"},{"name":"พัก","time_start":"10:50:00","time_end":"11:40:00"},{"name":"อังกฤษ ครูสุวพล","time_start":"11:40:00","time_end":"12:30:00"},{"name":"คณิตเพิ่มเติม","time_start":"12:30:00","time_end":"13:20:00"},{"name":"คณิตศาสตร์","time_start":"13:20:00","time_end":"14:10:00"}]},{"day":"Friday","class":[{"name":"เทคโนโลยี","time_start":"08:20:00","time_end":"09:10:00"},{"name":"สังคม","time_start":"09:10:00","time_end":"10:00:00"},{"name":"อังกฤษ","time_start":"10:00:00","time_end":"10:50:00"},{"name":"พัก","time_start":"10:50:00","time_end":"11:40:00"},{"name":"คุณธรรม","time_start":"11:40:00","time_end":"12:30:00"},{"name":"ลูกเสือ","time_start":"12:30:00","time_end":"13:20:00"},{"name":"ชุมนุม","time_start":"13:20:00","time_end":"14:10:00"}]}]}